setup.cfg
setup.py
sqlturk/__init__.py
sqlturk/migration.py
sqlturk.egg-info/PKG-INFO
sqlturk.egg-info/SOURCES.txt
sqlturk.egg-info/dependency_links.txt
sqlturk.egg-info/entry_points.txt
sqlturk.egg-info/requires.txt
sqlturk.egg-info/top_level.txt
sqlturk.egg-info/zip-safe