Metadata-Version: 1.0
Name: sqlturk
Version: 0.9.1
Summary: Database schema migration tool
Home-page: http://bitbucket.org/max/sqlturk/
Author: Max Ischenko
Author-email: ischenko@gmail.com
License: Apache License, Version 2.0
Keywords: sql database schema migration evolution migrate sqlalchemy
Platform: UNKNOWN
Classifier: Development Status :: 4 - Beta
Classifier: Operating System :: OS Independent
Classifier: Programming Language :: Python
Classifier: Intended Audience :: Developers
Classifier: License :: OSI Approved :: Apache Software License
Classifier: Topic :: Software Development
